appsync_tools/__init__.py
appsync_tools-2.0.5.dist-info/LICENSE
appsync_tools-2.0.5.dist-info/METADATA
appsync_tools-2.0.5.dist-info/WHEEL
appsync_tools-2.0.5.dist-info/top_level.txt
appsync_tools-2.0.5.dist-info/RECORD
