Metadata-Version: 2.1
Name: appsync-tools
Version: 2.0.5
Summary: Tools for handling appsync responses and routes.
Home-page: https://github.com/QuiNovas/appsync-tools
Author: Mathew Moon
Author-email: mmoon@quinovas.com
License: Apache 2.0
Platform: UNKNOWN
Classifier: Development Status :: 5 - Production/Stable
Classifier: Intended Audience :: Developers
Classifier: License :: OSI Approved :: Apache Software License
Classifier: Programming Language :: Python :: 3.8
License-File: LICENSE
Requires-Dist: typeguard
